ypyapi/__init__.py
ypyapi/chrome_api.py
ypyapi/file_api.py
ypyapi/image_api.py
ypyapi/sql_api.py
ypyapi/thread_api.py
ypyapi/util_api.py
ypyapi-0.0.37.dist-info/LICENSE
ypyapi-0.0.37.dist-info/METADATA
ypyapi-0.0.37.dist-info/WHEEL
ypyapi-0.0.37.dist-info/top_level.txt
ypyapi-0.0.37.dist-info/RECORD
