Metadata-Version: 2.1
Name: ypyapi
Version: 0.0.37
Summary: A collection of tools for Python
Home-page: http://pypi.python.org/pypi/ypyapi
Author: PingyanYang
Author-email: yangpingyan@gmail.com
License: MIT
Keywords: functional utility
Platform: UNKNOWN
Classifier: Intended Audience :: Developers
Classifier: License :: OSI Approved :: MIT License
Classifier: Natural Language :: English
Classifier: Programming Language :: Python :: 3
Classifier: Topic :: Utilities
Classifier: Operating System :: OS Independent
Requires-Python: >=3.5
Requires-Dist: selenium
